pycdisc/__init__.py
pycdisc/colors.json
pycdisc/main.py
pycdisc/ops.py
pycdisc-1.2.3.dist-info/METADATA
pycdisc-1.2.3.dist-info/WHEEL
pycdisc-1.2.3.dist-info/entry_points.txt
pycdisc-1.2.3.dist-info/top_level.txt
pycdisc-1.2.3.dist-info/RECORD
