Metadata-Version: 2.1
Name: pycdisc
Version: 1.2.3
Summary: just another mod to print strings in 256 colors in the terminal.
Home-page: https://gitlab.com/shindagger/string-color
Author: Andy Klier
Author-email: andyklier@gmail.com
Classifier: Programming Language :: Python :: 3
Classifier: License :: OSI Approved :: MIT License
Classifier: Operating System :: OS Independent
Requires-Dist: setuptools
Requires-Dist: columnar (>=1.3.1)
Requires-Dist: colorama
